vectors_likeablejuniper/__init__.py
vectors_likeablejuniper-0.0.7.dist-info/licenses/LICENSE
vectors_likeablejuniper-0.0.7.dist-info/METADATA
vectors_likeablejuniper-0.0.7.dist-info/WHEEL
vectors_likeablejuniper-0.0.7.dist-info/top_level.txt
vectors_likeablejuniper-0.0.7.dist-info/RECORD
