Metadata-Version: 2.4
Name: vectors_likeablejuniper
Version: 0.0.7
Summary: Vectors
Author-email: Noa Steffen <noa_steffen@hotmail.com>
License-Expression: MIT
Classifier: Programming Language :: Python :: 3
Classifier: Operating System :: OS Independent
Requires-Python: >=3.11.5
License-File: LICENSE
Dynamic: license-file
